MANIFEST.in
README.creole
setup.py
djangocms_widgets/__init__.py
djangocms_widgets/admin.py
djangocms_widgets/cms_plugins.py
djangocms_widgets/models.py
djangocms_widgets.egg-info/PKG-INFO
djangocms_widgets.egg-info/SOURCES.txt
djangocms_widgets.egg-info/dependency_links.txt
djangocms_widgets.egg-info/not-zip-safe
djangocms_widgets.egg-info/top_level.txt
djangocms_widgets/migrations/0001_initial.py
djangocms_widgets/migrations/__init__.py
djangocms_widgets_socialshareprivacy/__init__.py